{
  "_class": "symbolInstance",
  "booleanOperation": 0,
  "clippingMaskMode": 0,
  "do_objectID": "F8EB272B-A8EB-44E5-BE4F-10B9E28B43C8",
  "exportOptions": {
    "_class": "exportOptions",
    "do_objectID": "80212A01-06FF-40FB-9A4A-6083D14CD8E4",
    "exportFormats": [
    ],
    "includedLayerIds": [
    ],
    "layerOptions": 0,
    "shouldTrim": false
  },
  "frame": {
    "_class": "rect",
    "constrainProportions": false,
    "do_objectID": "2251937D-3624-4FB7-85BC-F03633EB562C",
    "height": 71,
    "width": 71,
    "x": 0,
    "y": 1
  },
  "hasClippingMask": false,
  "horizontalSpacing": 0,
  "isFixedToViewport": false,
  "isFlippedHorizontal": false,
  "isFlippedVertical": false,
  "isLocked": false,
  "isVisible": true,
  "layerListExpandedType": 0,
  "name": "#1",
  "nameIsFixed": true,
  "overrideValues": [
    {
      "_class": "overrideValue",
      "overrideName": "940BDDDD-8BA0-4249-AECD-E2E69C1200B3_symbolID",
      "value": "0964C22F-B0E0-4AEE-9771-07087CD8AC15"
    },
    {
      "_class": "overrideValue",
      "overrideName": "E3D5A8FC-0ED4-496B-9973-AA62EE892712_symbolID",
      "value": "FE587181-3B0F-439D-B31B-AD860F0EF995"
    }
  ],
  "resizingConstraint": 63,
  "resizingType": 0,
  "rotation": 0,
  "scale": 1,
  "shouldBreakMaskChain": false,
  "style": {
    "_class": "style",
    "do_objectID": "D370C4F4-907B-4841-ABA7-21B89090FDA6",
    "endMarkerType": 0,
    "miterLimit": 10,
    "startMarkerType": 0,
    "windingRule": 1
  },
  "symbolID": "A8BAF177-C8B6-4A8B-8480-5C30FCBD5962",
  "userInfo": {
    "com.animaapp.stc-sketch-plugin": {
      "kModelPropertiesKey": {
      }
    }
  },
  "verticalSpacing": 0
}