{
  "_class": "text",
  "attributedString": {
    "_class": "attributedString",
    "attributes": [
      {
        "_class": "stringAttribute",
        "attributes": {
          "MSAttributedStringColorAttribute": {
            "_class": "color",
            "alpha": 1,
            "blue": 0.8509803921568627,
            "green": 0.8196078431372549,
            "red": 0.7607843137254902
          },
          "MSAttributedStringFontAttribute": {
            "_class": "fontDescriptor",
            "attributes": {
              "name": "Ubuntu",
              "size": 21.6000017166138
            }
          },
          "kerning": 0.2592,
          "paragraphStyle": {
            "_class": "paragraphStyle",
            "alignment": 2
          }
        },
        "length": 3,
        "location": 0
      }
    ],
    "string": "Aug"
  },
  "automaticallyDrawOnUnderlyingPath": false,
  "booleanOperation": 0,
  "clippingMaskMode": 0,
  "do_objectID": "5D76372D-CA1B-47CB-A45A-3DFBAD9507C1",
  "dontSynchroniseWithSymbol": false,
  "exportOptions": {
    "_class": "exportOptions",
    "do_objectID": "AA6D74F8-B431-4D15-A549-6BC85B2A4802",
    "exportFormats": [
    ],
    "includedLayerIds": [
    ],
    "layerOptions": 0,
    "shouldTrim": false
  },
  "frame": {
    "_class": "rect",
    "constrainProportions": false,
    "do_objectID": "5BC3A6BB-C407-4425-A557-C5FE1B4C2EF5",
    "height": 24,
    "width": 51.84000411987313,
    "x": 604.8000480651865,
    "y": 2.273736754432321e-13
  },
  "glyphBounds": "{{6, 5}, {38, 20}}",
  "hasClippingMask": false,
  "isFixedToViewport": false,
  "isFlippedHorizontal": false,
  "isFlippedVertical": false,
  "isLocked": false,
  "isVisible": true,
  "layerListExpandedType": 0,
  "lineSpacingBehaviour": 2,
  "name": "Aug",
  "nameIsFixed": false,
  "resizingConstraint": 63,
  "resizingType": 0,
  "rotation": 0,
  "shouldBreakMaskChain": false,
  "style": {
    "_class": "style",
    "blur": {
      "_class": "blur",
      "center": "{0.5, 0.5}",
      "do_objectID": "D7D569F3-E7AD-4937-8900-7FB21CEAC21E",
      "isEnabled": false,
      "motionAngle": 0,
      "radius": 21.6000017166138,
      "saturation": 1,
      "type": 0
    },
    "do_objectID": "F9C70245-AFDA-45F4-AF49-5D087E17CD50",
    "endMarkerType": 0,
    "miterLimit": 10,
    "startMarkerType": 0,
    "textStyle": {
      "_class": "textStyle",
      "do_objectID": "9A20FA4A-4984-41E8-8C9D-5492AAED92E1",
      "encodedAttributes": {
        "MSAttributedStringColorAttribute": {
          "_class": "color",
          "alpha": 1,
          "blue": 0.8509803921568627,
          "green": 0.8196078431372549,
          "red": 0.7607843137254902
        },
        "MSAttributedStringFontAttribute": {
          "_class": "fontDescriptor",
          "attributes": {
            "name": "Ubuntu",
            "size": 21.6000017166138
          }
        },
        "kerning": 0.2592,
        "paragraphStyle": {
          "_class": "paragraphStyle",
          "alignment": 2
        }
      },
      "verticalAlignment": 0
    },
    "windingRule": 1
  },
  "textBehaviour": 1,
  "userInfo": {
    "com.animaapp.stc-sketch-plugin": {
      "kModelPropertiesKey": {
        "isAutoWidth": 0
      }
    }
  }
}