{
  "_class": "symbolInstance",
  "booleanOperation": 0,
  "clippingMaskMode": 0,
  "do_objectID": "CB08DFEE-B946-4189-B726-BDD666373B0C",
  "exportOptions": {
    "_class": "exportOptions",
    "do_objectID": "B84EEEF5-8764-4BEF-A014-BB46A35B770F",
    "exportFormats": [
    ],
    "includedLayerIds": [
    ],
    "layerOptions": 0,
    "shouldTrim": false
  },
  "frame": {
    "_class": "rect",
    "constrainProportions": false,
    "do_objectID": "2BD3E1F3-00BB-4CCA-A53A-40BEF9857A87",
    "height": 320,
    "width": 360,
    "x": 540,
    "y": 135
  },
  "hasClippingMask": false,
  "horizontalSpacing": 0,
  "isFixedToViewport": false,
  "isFlippedHorizontal": false,
  "isFlippedVertical": false,
  "isLocked": false,
  "isVisible": true,
  "layerListExpandedType": 0,
  "name": "#2",
  "nameIsFixed": true,
  "overrideValues": [
    {
      "_class": "overrideValue",
      "overrideName": "09EA4B0F-902C-4F82-B969-D12DFBF98D0B_stringValue",
      "value": "@Frank_Todd"
    }
  ],
  "resizingConstraint": 63,
  "resizingType": 0,
  "rotation": 0,
  "scale": 1,
  "shouldBreakMaskChain": false,
  "style": {
    "_class": "style",
    "do_objectID": "E9E7B2B2-ED72-40C1-8319-004A5F963806",
    "endMarkerType": 0,
    "miterLimit": 10,
    "startMarkerType": 0,
    "windingRule": 1
  },
  "symbolID": "9C46CBD9-9EAD-4FA9-B7A8-0EF6615EE71B",
  "userInfo": {
    "com.animaapp.stc-sketch-plugin": {
      "kModelPropertiesKey": {
      }
    }
  },
  "verticalSpacing": 0
}