{
  "_class": "symbolInstance",
  "booleanOperation": 0,
  "clippingMaskMode": 0,
  "do_objectID": "3129B502-54C1-43CA-BE37-F5C34C48BE7B",
  "exportOptions": {
    "_class": "exportOptions",
    "do_objectID": "16DBCD5C-6145-4F0A-9EED-FCFB77C66C41",
    "exportFormats": [
    ],
    "includedLayerIds": [
    ],
    "layerOptions": 0,
    "shouldTrim": false
  },
  "frame": {
    "_class": "rect",
    "constrainProportions": false,
    "do_objectID": "64FB9A27-7B37-4036-9175-2DCFA0223E8F",
    "height": 87,
    "width": 184,
    "x": 67,
    "y": 2
  },
  "hasClippingMask": false,
  "horizontalSpacing": 0,
  "isFixedToViewport": false,
  "isFlippedHorizontal": false,
  "isFlippedVertical": false,
  "isLocked": false,
  "isVisible": true,
  "layerListExpandedType": 0,
  "name": "#2",
  "nameIsFixed": true,
  "overrideValues": [
    {
      "_class": "overrideValue",
      "overrideName": "95DE521D-E543-4FB1-A1F3-EC769DEADD71_symbolID",
      "value": "F21DE825-FA3F-4488-8D23-78DC10D39ABB"
    }
  ],
  "resizingConstraint": 63,
  "resizingType": 0,
  "rotation": 0,
  "scale": 0.699999988079071,
  "shouldBreakMaskChain": false,
  "style": {
    "_class": "style",
    "blur": {
      "_class": "blur",
      "center": "{0.5, 0.5}",
      "do_objectID": "C3F1B12E-0B1B-49A0-8C87-64D091200C00",
      "isEnabled": false,
      "motionAngle": 0,
      "radius": 6.99999988079071,
      "saturation": 1,
      "type": 0
    },
    "do_objectID": "C5CE7BDC-E500-495E-BD7F-F8AD00F1B1A1",
    "endMarkerType": 0,
    "miterLimit": 10,
    "startMarkerType": 0,
    "windingRule": 1
  },
  "symbolID": "A577E17B-5179-4103-91E4-958B1B7B5051",
  "userInfo": {
    "com.animaapp.stc-sketch-plugin": {
      "kModelPropertiesKey": {
      }
    }
  },
  "verticalSpacing": 0
}