{
  "_class": "shapeGroup",
  "booleanOperation": 0,
  "clippingMaskMode": 0,
  "do_objectID": "E5DBB965-6DD2-4408-A1E3-A7254DC7BE99",
  "exportOptions": {
    "_class": "exportOptions",
    "do_objectID": "4206D8D2-FC29-4CAF-B6C1-CB672875ADDB",
    "exportFormats": [
    ],
    "includedLayerIds": [
    ],
    "layerOptions": 0,
    "shouldTrim": false
  },
  "frame": {
    "_class": "rect",
    "constrainProportions": false,
    "do_objectID": "AD77B2A7-EFE9-463A-9207-FA8003244916",
    "height": 89.72809667673712,
    "width": 90,
    "x": 0,
    "y": 0
  },
  "hasClickThrough": false,
  "hasClippingMask": false,
  "isFixedToViewport": false,
  "isFlippedHorizontal": false,
  "isFlippedVertical": false,
  "isLocked": false,
  "isVisible": true,
  "layerListExpandedType": 0,
  "layers": [
    {
      "class": "shapePath",
      "id": "578AF308-A3FC-4E73-A267-37FF4E09B8B4"
    },
    {
      "class": "shapePath",
      "id": "65E25089-7750-4573-A891-6B1CA2E09282"
    }
  ],
  "name": "Oval",
  "nameIsFixed": false,
  "resizingConstraint": 63,
  "resizingType": 0,
  "rotation": 0,
  "sharedStyleID": "C62EB368-B9F3-4E9A-9EAC-6D36CF034FD1",
  "shouldBreakMaskChain": false,
  "style": {
    "_class": "style",
    "blur": {
      "_class": "blur",
      "center": "{0.5, 0.5}",
      "do_objectID": "F8FCF699-7ABB-4C01-8499-83DACE978A91",
      "isEnabled": false,
      "motionAngle": 0,
      "radius": 6.99999988079071,
      "saturation": 1,
      "type": 0
    },
    "do_objectID": "80370A4C-4B1A-4821-9299-11096E02BB4C",
    "endMarkerType": 0,
    "fills": [
      {
        "_class": "fill",
        "color": {
          "_class": "color",
          "alpha": 1,
          "blue": 0.3529411764705883,
          "green": 0.2941176470588235,
          "red": 0.2588235294117647
        },
        "fillType": 0,
        "isEnabled": true,
        "noiseIndex": 0,
        "noiseIntensity": 0,
        "patternFillType": 1,
        "patternTileScale": 1
      }
    ],
    "miterLimit": 10,
    "startMarkerType": 0,
    "windingRule": 0
  },
  "userInfo": {
    "com.animaapp.stc-sketch-plugin": {
      "kModelPropertiesKey": {
      }
    }
  },
  "windingRule": 0
}