{
  "_class": "symbolInstance",
  "booleanOperation": 0,
  "clippingMaskMode": 0,
  "do_objectID": "AEBDB871-61D8-476F-A373-462E055B49E5",
  "exportOptions": {
    "_class": "exportOptions",
    "do_objectID": "A635F025-AA15-40D3-9DEB-F1B41E4C42C2",
    "exportFormats": [
    ],
    "includedLayerIds": [
    ],
    "layerOptions": 0,
    "shouldTrim": false
  },
  "frame": {
    "_class": "rect",
    "constrainProportions": false,
    "do_objectID": "50EA07F1-AC2A-4F45-BEAE-212E53D5547D",
    "height": 210,
    "width": 210,
    "x": 519,
    "y": 270
  },
  "hasClippingMask": false,
  "horizontalSpacing": 0,
  "isFixedToViewport": false,
  "isFlippedHorizontal": false,
  "isFlippedVertical": false,
  "isLocked": false,
  "isVisible": true,
  "layerListExpandedType": 0,
  "name": "#3",
  "nameIsFixed": true,
  "overrideValues": [
    {
      "_class": "overrideValue",
      "overrideName": "87EF607D-49C5-4B09-96B1-CE2DFCC67E9C_stringValue",
      "value": "$69.92"
    }
  ],
  "resizingConstraint": 63,
  "resizingType": 0,
  "rotation": 0,
  "scale": 1,
  "shouldBreakMaskChain": false,
  "style": {
    "_class": "style",
    "do_objectID": "C7ED0371-B968-4F1D-8F65-E94E0E503CC7",
    "endMarkerType": 0,
    "miterLimit": 10,
    "startMarkerType": 0,
    "windingRule": 1
  },
  "symbolID": "47F513E4-3BD7-4C7C-9532-2D7551529117",
  "userInfo": {
    "com.animaapp.stc-sketch-plugin": {
      "kModelPropertiesKey": {
      }
    }
  },
  "verticalSpacing": 0
}