{
  "_class": "text",
  "attributedString": {
    "_class": "attributedString",
    "attributes": [
      {
        "_class": "stringAttribute",
        "attributes": {
          "MSAttributedStringColorAttribute": {
            "_class": "color",
            "alpha": 1,
            "blue": 0.4083227040816326,
            "green": 0.3640872074321956,
            "red": 0.3135323541185532
          },
          "MSAttributedStringFontAttribute": {
            "_class": "fontDescriptor",
            "attributes": {
              "name": "Ubuntu-Bold",
              "size": 50
            }
          },
          "paragraphStyle": {
            "_class": "paragraphStyle",
            "alignment": 2,
            "allowsDefaultTighteningForTruncation": 0,
            "maximumLineHeight": 64,
            "minimumLineHeight": 64
          }
        },
        "length": 26,
        "location": 0
      }
    ],
    "string": "Frequently asked questions"
  },
  "automaticallyDrawOnUnderlyingPath": false,
  "booleanOperation": 0,
  "clippingMaskMode": 0,
  "do_objectID": "C0DA3F57-FA97-4548-8A6E-A777AF59280F",
  "dontSynchroniseWithSymbol": false,
  "exportOptions": {
    "_class": "exportOptions",
    "do_objectID": "C5352AB3-00D7-4093-B8BE-A6D7F54CDD11",
    "exportFormats": [
    ],
    "includedLayerIds": [
    ],
    "layerOptions": 0,
    "shouldTrim": false
  },
  "frame": {
    "_class": "rect",
    "constrainProportions": false,
    "do_objectID": "91E3FA28-9213-4751-8642-C7FB2FB1E444",
    "height": 64,
    "width": 657,
    "x": 392.0000000000001,
    "y": 106
  },
  "glyphBounds": "{{4, 13}, {651, 49}}",
  "hasClippingMask": false,
  "isFixedToViewport": false,
  "isFlippedHorizontal": false,
  "isFlippedVertical": false,
  "isLocked": false,
  "isVisible": true,
  "layerListExpandedType": 0,
  "lineSpacingBehaviour": 2,
  "name": "Frequently asked questions",
  "nameIsFixed": true,
  "resizingConstraint": 47,
  "resizingType": 0,
  "rotation": 0,
  "sharedStyleID": "F30C80E1-C319-41B1-A49E-86E535441A22",
  "shouldBreakMaskChain": false,
  "style": {
    "_class": "style",
    "do_objectID": "933A010F-A5D5-48ED-886F-B77FED12E5E8",
    "endMarkerType": 0,
    "miterLimit": 10,
    "startMarkerType": 0,
    "textStyle": {
      "_class": "textStyle",
      "do_objectID": "0F78EC1F-43A2-45ED-BB61-51EA2BE6AEF6",
      "encodedAttributes": {
        "MSAttributedStringColorAttribute": {
          "_class": "color",
          "alpha": 1,
          "blue": 0.4083227040816326,
          "green": 0.3640872074321956,
          "red": 0.3135323541185532
        },
        "MSAttributedStringFontAttribute": {
          "_class": "fontDescriptor",
          "attributes": {
            "name": "Ubuntu-Bold",
            "size": 50
          }
        },
        "paragraphStyle": {
          "_class": "paragraphStyle",
          "alignment": 2,
          "allowsDefaultTighteningForTruncation": 0,
          "maximumLineHeight": 64,
          "minimumLineHeight": 64
        }
      },
      "verticalAlignment": 0
    },
    "windingRule": 1
  },
  "textBehaviour": 0,
  "userInfo": {
    "com.animaapp.stc-sketch-plugin": {
      "kModelPropertiesKey": {
        "isAutoWidth": 1
      }
    }
  }
}