{
  "_class": "group",
  "booleanOperation": 0,
  "clippingMaskMode": 0,
  "do_objectID": "9C6AE2EF-76E6-424C-A6FE-EA647A8F2CEF",
  "exportOptions": {
    "_class": "exportOptions",
    "do_objectID": "A4A59B71-77C3-464E-A864-C6BC94309702",
    "exportFormats": [
    ],
    "includedLayerIds": [
    ],
    "layerOptions": 0,
    "shouldTrim": false
  },
  "frame": {
    "_class": "rect",
    "constrainProportions": false,
    "do_objectID": "22EAAC98-0826-4CAB-AA2F-98BBE7E8D350",
    "height": 413,
    "width": 1446,
    "x": 1,
    "y": 0
  },
  "hasClickThrough": false,
  "hasClippingMask": false,
  "isFixedToViewport": false,
  "isFlippedHorizontal": false,
  "isFlippedVertical": false,
  "isLocked": false,
  "isVisible": true,
  "layerListExpandedType": 0,
  "layers": [
    {
      "class": "rectangle",
      "id": "307E4B94-E5B6-40BE-A8EE-F59E36B58971"
    },
    {
      "class": "symbolInstance",
      "id": "A7BBA898-BAA3-46A8-A984-49578F34D982"
    },
    {
      "class": "symbolInstance",
      "id": "2BE7BC4B-AAC2-4911-993C-DFA94F4C870D"
    }
  ],
  "name": "smartphones",
  "nameIsFixed": true,
  "resizingConstraint": 63,
  "resizingType": 0,
  "rotation": 0,
  "shouldBreakMaskChain": false,
  "style": {
    "_class": "style",
    "do_objectID": "1CC11390-D8EC-408B-9CD2-E41E13FA4BC0",
    "endMarkerType": 0,
    "miterLimit": 10,
    "startMarkerType": 0,
    "windingRule": 1
  },
  "userInfo": {
    "com.animaapp.stc-sketch-plugin": {
      "kModelPropertiesKey": {
      }
    }
  }
}