{
  "_class": "shapePath",
  "booleanOperation": -1,
  "clippingMaskMode": 0,
  "do_objectID": "9099A756-E10A-4B2D-9BF0-09661F17B21B",
  "edited": true,
  "exportOptions": {
    "_class": "exportOptions",
    "do_objectID": "6811B6F5-11F5-4BC9-99CA-4EB6A01A291C",
    "exportFormats": [
    ],
    "includedLayerIds": [
    ],
    "layerOptions": 0,
    "shouldTrim": false
  },
  "frame": {
    "_class": "rect",
    "constrainProportions": false,
    "do_objectID": "2BCF1ADE-F2B8-4888-A978-F77B259781EF",
    "height": 25.56062710855331,
    "width": 26.77259185700125,
    "x": 135.9285004965249,
    "y": 119.7062909307399
  },
  "hasClippingMask": false,
  "isClosed": true,
  "isFixedToViewport": false,
  "isFlippedHorizontal": false,
  "isFlippedVertical": false,
  "isLocked": false,
  "isVisible": true,
  "layerListExpandedType": 0,
  "name": "Path",
  "nameIsFixed": false,
  "originalObjectID": "C8B4CD0C-97D0-4D1B-902A-8B8D3852217C",
  "pointRadiusBehaviour": 0,
  "points": [
    {
      "_class": "curvePoint",
      "cornerRadius": 0,
      "curveFrom": "{1, 1}",
      "curveMode": 1,
      "curveTo": "{1, 1}",
      "hasCurveFrom": false,
      "hasCurveTo": false,
      "point": "{1, 1}"
    },
    {
      "_class": "curvePoint",
      "cornerRadius": 0,
      "curveFrom": "{0.068249258160242229, 0.65838509316770233}",
      "curveMode": 1,
      "curveTo": "{0.068249258160242229, 0.65838509316770233}",
      "hasCurveFrom": false,
      "hasCurveTo": false,
      "point": "{0.068249258160242229, 0.65838509316770233}"
    },
    {
      "_class": "curvePoint",
      "cornerRadius": 0,
      "curveFrom": "{0, 0.11801242236024687}",
      "curveMode": 1,
      "curveTo": "{0, 0.11801242236024687}",
      "hasCurveFrom": false,
      "hasCurveTo": false,
      "point": "{0, 0.11801242236024687}"
    },
    {
      "_class": "curvePoint",
      "cornerRadius": 0,
      "curveFrom": "{0.75964391691393773, 0}",
      "curveMode": 1,
      "curveTo": "{0.75964391691393773, 0}",
      "hasCurveFrom": false,
      "hasCurveTo": false,
      "point": "{0.75964391691393773, 0}"
    },
    {
      "_class": "curvePoint",
      "cornerRadius": 0,
      "curveFrom": "{1, 1}",
      "curveMode": 1,
      "curveTo": "{1, 1}",
      "hasCurveFrom": false,
      "hasCurveTo": false,
      "point": "{1, 1}"
    }
  ],
  "resizingConstraint": 63,
  "resizingType": 0,
  "rotation": 0,
  "shouldBreakMaskChain": false,
  "style": {
    "_class": "style",
    "contextSettings": {
      "_class": "graphicsContextSettings",
      "blendMode": 0,
      "opacity": 0.5
    },
    "endMarkerType": 0,
    "fills": [
      {
        "_class": "fill",
        "color": {
          "_class": "color",
          "alpha": 1,
          "blue": 0.8509803921568627,
          "green": 0.8196078431372549,
          "red": 0.7607843137254902
        },
        "fillType": 0,
        "isEnabled": true,
        "noiseIndex": 0,
        "noiseIntensity": 0,
        "patternFillType": 1,
        "patternTileScale": 1
      }
    ],
    "miterLimit": 10,
    "startMarkerType": 0,
    "windingRule": 1
  },
  "userInfo": {
    "com.animaapp.stc-sketch-plugin": {
      "kModelPropertiesKey": {
      }
    }
  }
}