{
  "_class": "text",
  "attributedString": {
    "_class": "attributedString",
    "attributes": [
      {
        "_class": "stringAttribute",
        "attributes": {
          "MSAttributedStringColorAttribute": {
            "_class": "color",
            "alpha": 1,
            "blue": 0.8509803921568627,
            "green": 0.8196078431372549,
            "red": 0.7607843137254902
          },
          "MSAttributedStringFontAttribute": {
            "_class": "fontDescriptor",
            "attributes": {
              "name": "Ubuntu",
              "size": 12
            }
          },
          "kerning": 0.144,
          "paragraphStyle": {
            "_class": "paragraphStyle",
            "alignment": 2
          }
        },
        "length": 3,
        "location": 0
      }
    ],
    "string": "Oct"
  },
  "automaticallyDrawOnUnderlyingPath": false,
  "booleanOperation": 0,
  "clippingMaskMode": 0,
  "do_objectID": "7BF3D461-BE99-4651-ACF3-99898F19DACF",
  "dontSynchroniseWithSymbol": false,
  "exportOptions": {
    "_class": "exportOptions",
    "do_objectID": "B890FD33-F32F-47D3-A1CB-25941B3A69C5",
    "exportFormats": [
    ],
    "includedLayerIds": [
    ],
    "layerOptions": 0,
    "shouldTrim": false
  },
  "frame": {
    "_class": "rect",
    "constrainProportions": false,
    "do_objectID": "2D40E10C-B182-4D83-AE65-8B7838FAF12A",
    "height": 13,
    "width": 21,
    "x": 446.1999905586241,
    "y": 0
  },
  "glyphBounds": "{{0, 2}, {20, 10}}",
  "hasClippingMask": false,
  "isFixedToViewport": false,
  "isFlippedHorizontal": false,
  "isFlippedVertical": false,
  "isLocked": false,
  "isVisible": true,
  "layerListExpandedType": 0,
  "lineSpacingBehaviour": 2,
  "name": "Oct",
  "nameIsFixed": false,
  "resizingConstraint": 47,
  "resizingType": 0,
  "rotation": 0,
  "shouldBreakMaskChain": false,
  "style": {
    "_class": "style",
    "blur": {
      "_class": "blur",
      "center": "{0.5, 0.5}",
      "do_objectID": "19CEABA7-F9AC-4815-8FAE-57786B45BA0A",
      "isEnabled": false,
      "motionAngle": 0,
      "radius": 21.6000017166138,
      "saturation": 1,
      "type": 0
    },
    "do_objectID": "B9D2E755-FEBF-4FCC-B9EA-71D9D2A59C5B",
    "endMarkerType": 0,
    "miterLimit": 10,
    "startMarkerType": 0,
    "textStyle": {
      "_class": "textStyle",
      "do_objectID": "E13763EA-DAA6-43E2-8434-064FC2A16811",
      "encodedAttributes": {
        "MSAttributedStringColorAttribute": {
          "_class": "color",
          "alpha": 1,
          "blue": 0.8509803921568627,
          "green": 0.8196078431372549,
          "red": 0.7607843137254902
        },
        "MSAttributedStringFontAttribute": {
          "_class": "fontDescriptor",
          "attributes": {
            "name": "Ubuntu",
            "size": 12
          }
        },
        "kerning": 0.144,
        "paragraphStyle": {
          "_class": "paragraphStyle",
          "alignment": 2
        }
      },
      "verticalAlignment": 0
    },
    "windingRule": 1
  },
  "textBehaviour": 0,
  "userInfo": {
    "com.animaapp.stc-sketch-plugin": {
      "kModelPropertiesKey": {
        "isAutoWidth": 1
      }
    }
  }
}