{
  "_class": "symbolMaster",
  "backgroundColor": {
    "_class": "color",
    "alpha": 1,
    "blue": 1,
    "green": 1,
    "red": 1
  },
  "booleanOperation": 0,
  "changeIdentifier": 111,
  "clippingMaskMode": 0,
  "do_objectID": "5C2D20BE-8E1E-4258-871E-BD1AA7B707A1",
  "exportOptions": {
    "_class": "exportOptions",
    "exportFormats": [
    ],
    "includedLayerIds": [
    ],
    "layerOptions": 0,
    "shouldTrim": false
  },
  "frame": {
    "_class": "rect",
    "constrainProportions": false,
    "height": 198,
    "width": 420,
    "x": 15071,
    "y": 0
  },
  "hasBackgroundColor": false,
  "hasClickThrough": false,
  "hasClippingMask": false,
  "horizontalRulerData": {
    "_class": "rulerData",
    "base": 0,
    "guides": [
    ]
  },
  "includeBackgroundColorInExport": true,
  "includeBackgroundColorInInstance": false,
  "includeInCloudUpload": true,
  "isFixedToViewport": false,
  "isFlippedHorizontal": false,
  "isFlippedVertical": false,
  "isFlowHome": false,
  "isLocked": false,
  "isVisible": true,
  "layerListExpandedType": 0,
  "layers": [
    {
      "class": "rectangle",
      "id": "E183FB59-C28F-4ACD-A4C1-1AFC075443F4"
    },
    {
      "class": "symbolInstance",
      "id": "3227A837-A8C3-47BC-AB21-3CECB3ADA3B4"
    },
    {
      "class": "text",
      "id": "8F000859-21E6-4FBE-95BF-B1FE73C100C9"
    },
    {
      "class": "group",
      "id": "AE2AAA0B-7822-405D-A740-05A7DC786975"
    }
  ],
  "name": "Molecules / Dialog / v1",
  "nameIsFixed": false,
  "resizesContent": true,
  "resizingConstraint": 63,
  "resizingType": 0,
  "rotation": 0,
  "shouldBreakMaskChain": true,
  "style": {
    "_class": "style",
    "endMarkerType": 0,
    "miterLimit": 10,
    "startMarkerType": 0,
    "windingRule": 1
  },
  "symbolID": "AE06C132-0DDE-4764-AAC7-34ED361ED513",
  "userInfo": {
    "com.animaapp.stc-sketch-plugin": {
      "kModelPropertiesKey": {
      }
    }
  },
  "verticalRulerData": {
    "_class": "rulerData",
    "base": 0,
    "guides": [
    ]
  }
}